Workbook

Sheet Punto de equilibrio
C1: 190102475001
A2: COMPUFACIL COMPUTADORAS Y FACILIDADES CIA.LTDA.
A3: Estado de situación finaciera
C5: 2015 | D5: 2016 | E5: 2017 | F5: 2018 | G5: 2019 | H5: 2020
A6: ACTIVOS
A7: Activos Corrientes:
A8: Efectivo y equivalentes de efectivo | B8: Efectivo_y_equivalentes_de | C8: 3405.75 | D8: 224.8 | E8: 1679.16 | F8: 1271.49 | G8: 56057.07 | H8: 34732.422 | I8: ZONA DE GENERACIÓN DE RIQUEZA
A9: Inversiones financieras C/P | B9: Inversiones_financieras_C_P | C9: 0 | D9: 0 | E9: 0 | F9: 0 | G9: 0 | H9: 0
A10: Cuentas por cobrar | B10: Cuentas_por_cobrar | C10: 130600.21 | D10: 130600.21 | E10: 160768.44 | F10: 143191.27 | G10: 374114.41 | H10: 374446.62
A11: Inventarios | B11: Inventarios | C11: 103701.66 | D11: 93542.172 | E11: 102889.34 | F11: 46753.75 | G11: 584042.44 | H11: 17275
A12: Otros activos corrientes | B12: Otros_activos_corrientes | C12: 13782.57 | D12: 6173.3003 | E12: 9363.7695 | F12: 4844.7998 | G12: 214889.41 | H12: 0
A13: Total activos corrientes | B13: Total_activos_corrientes | C13: 251490.19 | D13: 230540.48 | E13: 274700.7 | F13: 196061.31 | G13: =SUM(G8:G12) -> 1229103.3 | H13: 426454.05
A14: Activos no corrientes:
A15: P.P.E Bruta | B15: P_P_E_Bruta | C15: 63185.219 | D15: 81459.961 | E15: 98117.727 | F15: 119806.72 | G15: 3421246 | H15: 175580.88
A16: Depreciación acumulada | B16: Depreciación_acumulada | C16: -46005.559 | D16: -56861.531 | E16: -65870.141 | F16: -65390.461 | G16: 1250328.2 | H16: -108965.64
A17: P.P.E Neta | B17: P_P_E_Neta | C17: 17179.66 | D17: 24598.43 | E17: 32247.586 | F17: 54416.258 | G17: 217091775 | H17: 66615.234
A18: Inversiones financieras L/P | B18: Inversiones_financieras_L_P | C18: 0 | D18: 0 | E18: 0 | F18: 0 | G18: 0 | H18: 0
A19: Otros activos no corrientes | B19: Otros_activos_no_corrientes | C19: 0 | D19: 0 | E19: 0 | F19: 0 | G19: 43275.45 | H19: 0
A20: Total activos no corrientes | B20: Total_activos_no_corrientes | C20: 17179.66 | D20: 24598.43 | E20: 32247.586 | F20: 54416.258 | G20: 2214193.2 | H20: 66615.234
A21: TOTAL ACTIVOS | B21: TOTAL_ACTIVOS | C21: 268669.85 | D21: 255138.91 | E21: 306948.29 | F21: 250477.56 | G21: 3443296.5 | H21: 493069.28
A22: PASIVO Y CAPITAL
A23: Pasivos corrientes :
A24: Obligaciones financieras de corto plazo | B24: Obligaci_financi_cort_plaz | C24: 0 | D24: 0 | E24: 0 | F24: 42079.461 | G24: 0 | H24: 0
A25: Cuentas por pagar / Proveedores | B25: Cuentas_pagar___Proveedores | C25: 35012.488 | D25: 25586.42 | E25: 18344.4 | F25: 29538.26 | G25: 1083741 | H25: 0
A26: Otros pasivos corrientes | B26: Otros_pasivos_corrientes | C26: 13602.74 | D26: 6035.5498 | E26: 3609.6799 | F26: 6003.46 | G26: 417199.5 | H26: 0
A27: Total pasivos corrientes | B27: Total_pasivos_corrientes | C27: 48615.229 | D27: 31621.97 | E27: 21954.08 | F27: 77621.181 | G27: 1797580.1 | H27: 0
A28: Pasivos no corrientes:
A29: Obligaciones financieras L/P | B29: Obligaciones_financieras_L_P | C29: 92149.758 | D29: 92149.758 | E29: 162287.64 | F29: 58570.281 | G29: 451915.25 | H29: 252430.3
A30: Otros pasivos no corrientes | B30: Otros_pasivos_no_corrientes | C30: 0 | D30: 43011.809 | E30: 36991.031 | F30: 0 | G30: 403256.41 | H30: 0
A31: Total pasivos no corrientes | B31: Total_pasivos_no_corrient | C31: 92149.758 | D31: 135161.57 | E31: 199278.67 | F31: 58570.281 | G31: 855171.62 | H31: 252430.3
A32: Total pasivos | B32: Total_pasivos | C32: 140764.99 | D32: 166783.54 | E32: 221232.75 | F32: 136191.46 | G32: 2652751.8 | H32: 252430.3
A33: Capital :
A34: Capital | B34: Capital | C34: 20680 | D34: 20680 | E34: 20680 | F34: 20680 | G34: 832316 | H34: 20680
A35: Reservas | B35: Reservas_ | C35: 0 | D35: 0 | E35: 0 | F35: 0 | G35: 20995.141 | H35: 0
A36: Utilidades retenidas | B36: Utilidades_retenidas | C36: 96717.773 | D36: 96717.773 | E36: 60657.25 | F36: 65035.539 | G36: -60976.367 | H36: 92757.156
A37: Utilidad del ejercicio | C37: 10507.09 | D37: -29042.4 | E37: 4378.29 | F37: 28570.561 | G37: -1789.72 | H37: 127201.82
A38: Total capital | B38: Total_capital | C38: 127904.86 | D38: 88355.373 | E38: 85715.54 | F38: 114286.1 | G38: 790545.06 | H38: 240638.98
A39: TOTAL PASIVOS Y CAPITAL | B39: TOTAL_PASIVOS_Y_CAPITAL | C39: 268669.85 | D39: 255138.91 | E39: 306948.29 | F39: 250477.56 | G39: 3443296.8 | H39: 493069.27
C40: 0.001953125 | D40: -0.003616333 | E40: 0.0032958984 | F40: -0.0017089844 | G40: 0.0092773438 | H40: -0.0078125
A43: COMPUFACIL COMPUTADORAS Y FACILIDADES CIA.LTDA. | J43: ENFOQUE CONTABILIDAD GERENCIAL
A44: Estado de Resultado
A45: NIVEL DE VENTAS 8644 UNIDADES | J45: TOTALES | L45: UNITARIOS
C46: 2015 | D46: 2016 | E46: 2017 | F46: 2018 | G46: 2019 | H46: 2020 | J46: Costos Fijos | K46: Costos Variables | L46: CVU
A47: Ingresos | B47: Ingresos_ | C47: 672177.62 | D47: 373486.41 | E47: 481311.44 | F47: 676965.06 | G47: 2465163 | H47: 1799479.8 | N47: Costo Fijo Unitario CFU a un nivel de ventas de 10199 UNIDADES | S47: Costo Fijo Unitario CFU a un nivel de ventas de 8644 UNIDADES
A48: Costo de ventas | B48: Costo_de_ventas | C48: 502087.31 | D48: 207300.8 | E48: 266702.03 | F48: 398476.72 | G48: 1109092.9 | H48: 968683.44 | J48: =G48*20% -> 221818.58 | K48: =G48*80% -> 887274.3 | L48: =K48/$Q$64 -> 35.992521 | N48: =J48 -> 221818.58 | O48: =N48/N49 -> 4.2369113 | S48: =J48 -> 221818.58 | T48: =S48/S49 -> 8.9981301
A49: Utilidad bruta en ventas (Margen bruto) | B49: Utilidad_bruta_en_ventas | C49: 170090.31 | D49: 166185.61 | E49: 214609.41 | F49: 278488.34 | G49: =G47-G48 -> 1356070.1 | H49: 830796.31 | N49: =N106 -> 52353.839 | S49: =G106 -> 24651.63
A50: Gastos de Administración | B50: Gastos_de_administración | C50: 128454.12 | D50: 172298.06 | E50: 174914.45 | F50: 204356.95 | G50: 1024585.9 | H50: 584424.56 | J50: =G50*80% -> 819668.7 | K50: =G50*20% -> 204917.18 | L50: =K50/$Q$64 -> 8.3125203 | N50: Costo Promedio Unitario CPU a un nivel de ventas de 10199 UNIDADES | S50: Costo Promedio Unitario CPU a un nivel de ventas de 8644 UNIDADES
A51: Gastos de Venta | C51: 18912.32 | D51: 12402.93 | E51: 18220.049 | F51: 18207.189 | G51: 28378.289 | H51: 51522.641 | J51: =G51*30% -> 8513.4867 | K51: =G51*70% -> 19864.802 | L51: =K51/$Q$64 -> 0.80582105 | N51: CVU + CFU = CPU | S51: CVU + CFU = CPU
A52: Depreciaciones y amortizaciones | B52: Depreciaciones_y_amortizaciones | C52: 10362.569 | D52: 10527.03 | E52: 10527.04 | F52: 10267.65 | G52: 431939.31 | H52: 31844.98 | J52: =G52*100% -> 431939.31 | N52: =L48 -> 35.992521 | O52: + | P52: =O48 -> 4.2369113 | Q52: =N52+P52 -> 40.229432 | S52: =L48 -> 35.992521 | T52: + | U52: =T48 -> 8.9981301 | V52: =S52+U52 -> 44.990651
A53: Otros ingresos / gastos neto | B53: Otros_ingresos___gastos_neto | C53: 0 | D53: 0 | E53: 0 | F53: 0 | G53: 238134.73 | H53: 0 | J53: =G53*25% -> 59533.684 | K53: =G53*75% -> 178601.05
A54: Utilidad antes de intereses e impuestos o utilidad operacional | C54: 12361.306 | D54: -29042.413 | E54: 10947.864 | F54: 45656.551 | G54: =G49-G50-G51-G52-G53 -> -366968.09 | H54: 163004.13
A55: Gastos financieros | B55: Gastos_financieros | C55: 0 | D55: 0 | E55: 6569.5801 | F55: 17085.98 | G55: 92055.688 | H55: 35802.383 | J55: =G55 -> 92055.688
A56: Utilidad antes de impuestos UAI | C56: 12361.306 | D56: -29042.413 | E56: 4378.2842 | F56: 28570.57 | G56: =G54-G55 -> -459023.77 | H56: 127201.75
A57: Participación 15% Utilidad trabajadores | C57: 1854.1899 | D57: 0 | E57: 656.73999 | F57: 4285.5801 | G57: 2586.8601 | H57: 19080.27
A58: Impuestos | B58: Impuestos | C58: 4189.27 | D58: 4990.6001 | E58: 6176.3198 | F58: 6905.4702 | G58: 7652.0601 | H58: 43196.441
A59: Utilidad del período (Utilidad neta o Utilidad después de impuestos | C59: 6317.8457 | D59: -34033.013 | E59: -2454.7756 | F59: 17379.52 | G59: =G56-G57-G58 -> -469262.69 | H59: 64925.035 | J59: =SUM(J47:J58) -> 1633529.4 | K59: =SUM(K47:K58) -> 1290657.3 | L59: =J59+K59 -> 2924186.8 | M59: =G48+G50+G51+G52+G55-L59 -> -238134.73
C60: -4189.2441 | D60: -4990.6128 | E60: -6833.0657 | F60: -11191.041 | H60: -62276.785
J61: Producto A | K61: PVU. | L61: 100 | O61: # UNIDADES VENDIDAS | Q61: =G47 -> 2465163
K62: CVU. | L62: CVT | M62: =K59 -> 1290657.3 | N62: =M62/M63 -> 52.355862 | Q62: =L61 -> 100
A63: COMPUFACIL COMPUTADORAS Y FACILIDADES CIA.LTDA. | L63: X | M63: =Q64 -> 24651.63
A64: Costo de Ventas | Q64: =Q61/Q62 -> 24651.63 | R64: UNIDADES
A65: º | C65: 2015 | D65: 2016 | E65: 2017 | F65: 2018 | G65: 2019 | H65: 2020
A66: Costo de ventas
A67: Inventario Inicial | B67: Inv_Inicial | C67: 220230.97 | D67: 103701.66 | E67: 69648.531 | F67: 102889.34 | G67: 238408.89 | H67: 16000
A68: Compras | B68: Compras | C68: 385558 | D68: 197141.31 | E68: 299942.84 | F68: 342341.12 | G68: 1454726.4 | H68: 969958.44
A69: Inventario Final | B69: Inv_Final | C69: -103701.66 | D69: -93542.172 | E69: -102889.34 | F69: -46753.75 | G69: 584042.44 | H69: -17275
A70: Otras cuentas de Costo de Venta | B70: Otros_Costos | C70: 0 | D70: 0 | E70: 0 | F70: 0 | G70: 0 | H70: 0
A71: Total Costo de Venta | C71: 502087.31 | D71: 207300.8 | E71: 266702.04 | F71: 398476.71 | G71: =SUM(G67:G70) -> 2277177.7 | H71: 968683.44
C72: 0 | D72: 0 | E72: 0.0078125 | F72: -0.0078125 | G72: 0 | H72: 0
A74: 1. Determine el punto de equilibrio operativo, para cada ejercicio económico.
A76: X | G76: = | I76: CF
I77: PVU | J77: - | K77: CVU
G78: = | I78: =J59 -> 1633529.4
I79: =L61 -> 100 | J79: - | K79: =N62 -> 52.355862
G80: = | I80: =I78 -> 1633529.4
J81: =I79-K79 -> 47.644138
G82: = | I82: =I80/J81 -> 34286.053 | J82: UNIDADES
A84: 2. Determine el Margen de contribución, para cada ejercicio económico.
A85: MCU | G85: =J81 -> 47.644138
A86: MCT | G86: =G85*I82 -> 1633529.4
G88: MCT | I88: = | J88: CFT
G89: =G86 -> 1633529.4 | I89: = | J89: =J59 -> 1633529.4
A91: 3. Determine la utilidad deseada, para cada ejercicio económico
A92: Planeación utilidades 25% de rendimiento sobre la inversión en activos
A93: Rendimiento sobre activos= | G93: Activos totales | I93: x | J93: rendimiento deseado
A94: Rendimiento sobre activos= | G94: =G21 -> 3443296.5 | I94: x | J94: 0.25 | K94: = | L94: =G94*J94 -> 860824.12
A96: X | G96: = | I96: CF + UD
I97: PVU | J97: - | K97: CVU
A98: X | G98: = | I98: =J59 -> 1633529.4 | J98: + | K98: =L94 -> 860824.12
I99: =L61 -> 100 | J99: - | K99: =N62 -> 52.355862
G100: = | J100: =I98+K98 -> 2494353.6
J101: =I99-K99 -> 47.644138
G102: = | I102: =J100/J101 -> 52353.839
K105: Punto de equilibrio | N105: 25% de rendimiento sobre activos | Q105: Propuesta Mario Luis
A106: Nivel ventas | G106: =Q64 -> 24651.63 | J106: =+K106-G106 -> 9634.4228 | K106: =I82 -> 34286.053 | M106: =+N106-K106 -> 18067.787 | N106: =I102 -> 52353.839 | P106: =+Q106-N106 -> 7853.0759 | Q106: ='Adminis CxC'!C18 -> 60206.915
C107: 2015 | D107: 2016 | E107: 2017 | F107: 2018 | G107: 2019 | I107: Análisis vertical 2019 | K107: 2019 | L107: Análisis vertical 2019 | N107: 2022 | O107: Análisis vertical 2022 | Q107: 2022 ML | R107: Análisis vertical 2022 ML | T107: Análisis horizontal 2022 vs 2022 ML
A108: Ingresos | B108: Ingresos_ | C108: 672177.62 | D108: 373486.41 | E108: 481311.44 | F108: 676965.06 | G108: 2465163 | I108: =G108/$G$108 -> 1 | K108: =K106*I79 -> 3428605.3 | L108: =K108/$G$108 -> 1.390823 | N108: =N106*Q62 -> 5235383.9 | O108: =N108/$N$108 -> 1 | Q108: ='Adminis CxC'!G18 -> 6020691.5 | R108: =Q108/$Q$108 -> 1 | T108: =Q108/N108-1 -> 0.15 | U108: =Q108-N108 -> 785307.59
A109: Costo de ventas | B109: Costo_de_ventas | C109: 502087.31 | D109: 207300.8 | E109: 266702.03 | F109: 398476.72 | G109: 1109092.9 | I109: =G109/$G$108 -> 0.44990651 | K109: =K106*L48+J48 -> 1455860 | L109: =K109/$G$108 -> 0.59057354 | N109: =N106*L48+J48 -> 2106165.2 | O109: =N109/$N$108 -> 0.40229432 | Q109: =-'Adminis CxC'!G20 -> 2388817.2 | R109: =Q109/$Q$108 -> 0.39676791 | T109: =Q109/N109-1 -> 0.1342022 | U109: =Q109-N109 -> 282652
A110: Utilidad bruta en ventas (Margen bruto) | B110: Utilidad_bruta_en_ventas | C110: 170090.31 | D110: 166185.61 | E110: 214609.41 | F110: 278488.34 | G110: =G108-G109 -> 1356070.1 | I110: =G110/$G$108 -> 0.55009349 | K110: =K108-K109 -> 1972745.2 | L110: =K110/$G$108 -> 0.80024941 | N110: =N108-N109 -> 3129218.7 | O110: =N110/$N$108 -> 0.59770568 | Q110: =Q108-Q109 -> 3631874.3 | R110: =Q110/$Q$108 -> 0.60323209 | T110: =Q110/N110-1 -> 0.16063294 | U110: =Q110-N110 -> 502655.59
A111: Gastos de Administración | B111: Gastos_de_administración | C111: 128454.12 | D111: 172298.06 | E111: 174914.45 | F111: 204356.95 | G111: =G106*L50+J50 -> 1024585.9 | I111: =G111/$G$108 -> 0.41562602 | K111: =K106*L50+J50 -> 1104672.2 | L111: =K111/$G$108 -> 0.44811325 | N111: =N106*L50+J50 -> 1254861.1 | O111: =N111/$N$108 -> 0.23968845 | Q111: =Q106*L50+J50 -> 1320139.9 | R111: =Q111/$Q$108 -> 0.21926716 | T111: =Q111/N111-1 -> 0.052020782 | U111: =Q111-N111 -> 65278.853
...

Sheet Adminis CxC
A1: ADMINISTRACIÓN DE CUENTAS POR COBRAR
E3: Datos actuales | F3: Cvu (Costo variable unitario) | G3: ='Punto de equilibrio'!N52 -> 35.992521
A4: Datos | F4: Cpu (Costo promedio unitario) | G4: ='Punto de equilibrio'!Q52 -> 40.229432
F5: Pvu (Precio de venta unitario) | G5: 100
A7: Condiciones de crédito actuales | B7: % Descuento ofrecido | C7: 0.08 | E7: Supuesto decisión corto plazo | F7: Quienes aprovechan el Descuento | G7: 0.8
B8: Nuevo plazo de pago | F8: Crecimiento en ventas | G8: 0.15
B9: PMC (Período medio de cobro) | C9: 45 | F9: PMC (Período medio de cobro) | G9: 35 | I9: =25000000/400000 -> 62.5
B10: Ventas a crédito (unidades) | C10: ='Punto de equilibrio'!N106 -> 52353.839 | F10: Gastos cuentas incobrables % | G10: 0.045
B11: Gastos cuentas incobrables % | C11: 0.08 | F11: Rendimiento requerido por la inversión | G11: 0.13
F12: Incremento en ventas (unidades) | G12: =C10*G8 -> 7853.0759
A15: 1) Calcular la Contribución de las Utilidades
A16: a) Método Largo
A17: Plan Propuesto
A18: Ingresos por ventas | C18: =C10+G12 -> 60206.915 | D18: X | E18: =G5 -> 100 | G18: =C18*E18 -> 6020691.5
A19: Menos: | B19: Costos variables | C19: =C10+G12 -> 60206.915 | D19: X | E19: =G3 -> 35.992521 | F19: =C19*E19 -> 2166998.6
B20: Costos Fijos* | F20: =F35*C10 -> 221818.57 | G20: =-(F19+F20) -> -2388817.2
B21: Utilidad sobre ventas | G21: =G18+G20 -> 3631874.3 | H21: =G21/G18 -> 0.60323209
A23: Plan actual
A24: Ingresos por ventas | C24: =C10 -> 52353.839 | D24: X | E24: =G5 -> 100 | G24: =C24*E24 -> 5235383.9
A25: Menos: | B25: Costos variables | C25: =C10 -> 52353.839 | D25: X | E25: =G3 -> 35.992521 | F25: =C25*E25 -> 1884346.6
B26: Costos Fijos* | F26: =F35*C10 -> 221818.57 | G26: =-(F25+F26) -> -2106165.2
B27: Utilidad sobre ventas | G27: =G24+G26 -> 3129218.7 | H27: =G27/G24 -> 0.59770568
B29: Utilidad Marginal en Ventas = Utilidad sobre ventas Plan Propuesto - Utilidad sobre ventas Plan Actual | G29: =G21-G27 -> 502655.59
B31: * Cálculo de los Costos Fijos: | F31: CUP = Costo Unitario Promedio | J31: =C10 -> 52353.839 | K31: =J31*1.12 -> 58636.3
F32: CFU = Costo Fijo Unitario | I32: Costos fijos totales | J32: 25000000 | K32: 25000000
F33: CVU = Costo Variable Unitario
B34: CUP = CFU + CVU ⇒ CFU = CUP − CUV | F34: CFT = Costos Fijos Totales
B35: CFU = | C35: =G4 -> 40.229432 | D35: - | E35: =G3 -> 35.992521 | F35: =C35-E35 -> 4.2369113 | I35: Costos fijos unitarios | J35: =J32/J31 -> 477.5199 | K35: =K32/K31 -> 426.35705
B37: CFT = CFU *UnidadesBA se ⇒
B38: CFT= | C38: =F35 -> 4.2369113 | D38: * | E38: =$C$17 -> 0 | F38: =C38*E38 -> 0 | I38: Costos promedio unitario= | J38: =J40+J44 -> 513.51242 | K38: =K40+K44 -> 462.34957
A40: a) Método abreviado | I40: Costo variable unitario | J40: =G3 -> 35.992521 | K40: =G3 -> 35.992521
B41: Calcular Utilidad Marginal en Ventas ( UMV ) por dos métodos: | I41: Costos variables totales | J41: =J31*J40 -> 1884346.6 | K41: =K31*K40 -> 2110468.2
B43: 1. Por unidad | I43: Costos fijos totales | J43: =J32 -> 25000000 | K43: =K32 -> 25000000
B44: UMV = (PVU − CVU)ΔX | I44: Costos fijos unitarios | J44: =J35 -> 477.5199 | K44: =K35 -> 426.35705
B45: UMV = | C45: =G5 -> 100 | D45: - | E45: =G3 -> 35.992521 | F45: =G12 -> 7853.0759 | G45: =(C45-E45)*F45 -> 502655.59
B47: 2. Por monetario
B48: UMV= [ 1 - (Cvt/Ventas)] Δ Ventas | C48: 1 | D48: - | E48: =F25 -> 1884346.6 | F48: =G18-G24 -> 785307.59 | G48: =(1-(E48/E49))*F48 -> 502655.59
E49: =G24 -> 5235383.9
A51: 2) Calcular el Costo de Inversión Marginal en Cuentas por Cobrar (CIMCC)
A52: a) Cálculo de la Inversión Promedio en Cuentas por Cobrar (IPCC) Plan presente y Plan Propuesto
B54: Inversión Promedio en Cuentas por Cobrar (IPCC) Plan presente
B55: IPCC= (Costo de Venta)/RCC ⇒ IPCC = (CPU * X) / (360/PMC) | E55: =F58 -> 2106165.2 | F55: =E55/E56 -> 263270.65
E56: =F59 -> 8
B58: En donde Costo de Venta = CPU * X | C58: ='Punto de equilibrio'!Q52 -> 40.229432 | D58: * | E58: =C24 -> 52353.839 | F58: =C58*E58 -> 2106165.2
B59: En donde Rotación cuentas por cobrar RCC = 360 / PCM | C59: 360 | D59: / | E59: =C9 -> 45 | F59: =C59/E59 -> 8
B61: Inversión Promedio en Cuentas por Cobrar (IPCC) Plan propuesto
B62: IPCC= (Costo de Venta)/RCC ⇒ IPCC = (CPU * X) / (360/PMC) | E62: =F19+F20 -> 2388817.2 | F62: =E62/E63 -> 232246.12
E63: =F66 -> 10.285714
B65: En donde Costo de Venta = CPU * X | C65: =-G20/C19 -> 39.676791 | D65: * | E65: =C18 -> 60206.915 | F65: =C65*E65 -> 2388817.2
B66: En donde Rotación cuentas por cobrar RCC = 360 / PCM | C66: 360 | D66: / | E66: =G9 -> 35 | F66: =C66/E66 -> 10.285714
B69: Inversión Marginal en Cuentas por Cobrar (IMCC) = IPCC Plan Propuesto - IPCC Plan Actual
B70: Inversión Marginal en Cuentas por Cobrar (IMCC) = | C70: =F62 -> 232246.12 | D70: - | E70: =F55 -> 263270.65 | F70: =C70-E70 -> -31024.534
B72: Costo de la Inversión marginal en Cuentas por Cobrar
B73: CIMCC = IMCC * RendimientoRequerido | C73: =F70 -> -31024.534 | D73: * | E73: =G11 -> 0.13 | F73: =C73*E73 -> -4033.1894
B76: Determinar Costo Cuentas Malas Marginales (CCMM)
B77: Plan propuesto
B78: CCMMpp = ( X * Pvu ) * Nivel propuesto CCMM % | C78: =C10+G12 -> 60206.915 | D78: * | E78: =G5 -> 100 | F78: =G10 -> 0.045 | G78: =(C78*E78)*F78 -> 270931.12 | H78: a)
B80: Plan actual
B81: CCMMpa = ( X * Pvu ) * Nivel actual CCMM % | C81: =C10 -> 52353.839 | D81: * | E81: =G5 -> 100 | F81: =C11 -> 0.08 | G81: =(C81*E81)*F81 -> 418830.72 | H81: b)
B82: Costo Cuentas Malas Marginales (CCMM) | F82: =IF(G82<0, "!!AHORRO!! ⇒","xxGASTOxx ⇒") -> !!AHORRO!! ⇒ | G82: =G78-G81 -> -147899.6 | H82: c) = a - b
A85: 3) Costo del Descuento por pronto pago (CDPP)
B87: Costo del Descuento por pronto pago (CDPP)
B88: CDPP = ( %DsctoOfrecido ) ( QuienesaprovechanelDescuento )( Pvu * X ) | C88: =C7 -> 0.08 | D88: * | E88: =G7 -> 0.8 | F88: =G5*(C10+G12) -> 6020691.5 | G88: =C88*E88*F88 -> 385324.26
A91: 4) Decisión
B92: Utilidad Marginal en ventas | C92: UMV | D92: = | E92: =G45 -> 502655.59
A93: Mas: | B93: Costo de Inversión Marginal en Cuentas por Cobrar | C93: CIMCC | D93: = | E93: =-F73 -> 4033.1894
A94: Mas: | B94: Costo Cuentas Malas Marginales | C94: CCMM | D94: = | E94: =-G82 -> 147899.6
A95: Menos: | B95: Costo del Descuento por pronto pago | C95: CDPP | D95: = | E95: =-G88 -> -385324.26
B96: Utilidad Neta Marginal | D96: = | E96: =SUM(E92:E95) -> 269264.12
A99: Solución:
E100: Loja, 28 de mayo 2022
A101: Estimado Mario Luis:
A103: Una vez que revise todas las condiciones, si acepto su oferta de realizar el descuento por pronto pago. Por favor enviar correo de aprobación.
A105: Atentamente,
A109: Hans
A110: C./c. Accionista Mayoritario
D113: Plan Propuesto | E113: Plan Presente | F113: Diferencia
A114: Contribución de las Utilidades | D114: =G21 -> 3631874.3 | E114: =G27 -> 3129218.7 | F114: =D114-E114 -> 502655.59
A116: Costo de Inversión Marginal en Cuentas por Cobrar (CIMCC) | D116: =F62 -> 232246.12 | E116: =F55 -> 263270.65 | F116: =(D116-E116) -> -31024.534 | G116: =F73 -> -4033.1894
A117: Costo Cuentas Malas Marginales (CCMM) | D117: =G78 -> 270931.12 | E117: =G81 -> 418830.72 | F117: =D117-E117 -> -147899.6
A118: Costo del Descuento por pronto pago (CDPP) | D118: =G88 -> 385324.26
A136: 1. Debemos comparar la utilidad de ventas del plan presente frente a la utilidad en ventas del plan propuesto para cuantificar el incremento de utilidades. Este incremento deberá ser mayor siempre al costo del descuento por pronto pago. | E136: 2. Al realizar un descuento por pronto pago (CDPP), la Administración pretende bajar el periodo medio de cobro (PMC) de 45 días a 35 días, lo cual significa que la empresa tendrá menos dinero amortizado en cuentas por cobrar. En el ejemplo de la gráfica esa inversión amortizada en cuentas por cobrar se disminuyó en $31,024,53. Esa disminución representa dinero que la empresa obtendrá más pronto y lo cual medido a costo de oportunidad la empresa podría hacerlo trabajar al 13%.
A155: 3. La empresa al bajar el Periodo Medio de Cobro (PMC) tendrá la ventaja de bajar la morosidad e incobrabilidad, producto del descuento por pronto pago. En este caso la empresa dejará de registrar como gasto de deterioro de cartera $147,899,60. | E155: 4. Así como la empresa subió su utilidad en ventas producto del descuento por pronto pago (CDPP), también debe cuantificar el costo que tendrá esta decisión. Para el ejemplo anterior esa decisión le cuesta $385,324,26 mil.
